{
  "Resources": {
    "PostsTableC82B36F0": {
      "Type": "AWS::DynamoDB::Table",
      "Properties": {
        "AttributeDefinitions": [
          {
            "AttributeName": "id",
            "AttributeType": "S"
          }
        ],
        "BillingMode": "PAY_PER_REQUEST",
        "KeySchema": [
          {
            "AttributeName": "id",
            "KeyType": "HASH"
          }
        ]
      },
      "UpdateReplacePolicy": "Delete",
      "DeletionPolicy": "Delete",
      "Metadata": {
        "aws:cdk:path": "Project03CdkBasicStack/PostsTable/Resource"
      }
    },
    "PostsFunctionServiceRoleF2DB8406": {
      "Type": "AWS::IAM::Role",
      "Properties": {
        "AssumeRolePolicyDocument": {
          "Statement": [
            {
              "Action": "sts:AssumeRole",
              "Effect": "Allow",
              "Principal": {
                "Service": "lambda.amazonaws.com"
              }
            }
          ],
          "Version": "2012-10-17"
        },
        "ManagedPolicyArns": [
          {
            "Fn::Join": [
              "",
              [
                "arn:",
                {
                  "Ref": "AWS::Partition"
                },
                ":iam::aws:policy/service-role/AWSLambdaBasicExecutionRole"
              ]
            ]
          }
        ]
      },
      "Metadata": {
        "aws:cdk:path": "Project03CdkBasicStack/PostsFunction/ServiceRole/Resource"
      }
    },
    "PostsFunctionServiceRoleDefaultPolicyACA3B729": {
      "Type": "AWS::IAM::Policy",
      "Properties": {
        "PolicyDocument": {
          "Statement": [
            {
              "Action": [
                "dynamodb:BatchGetItem",
                "dynamodb:BatchWriteItem",
                "dynamodb:ConditionCheckItem",
                "dynamodb:DeleteItem",
                "dynamodb:DescribeTable",
                "dynamodb:GetItem",
                "dynamodb:GetRecords",
                "dynamodb:GetShardIterator",
                "dynamodb:PutItem",
                "dynamodb:Query",
                "dynamodb:Scan",
                "dynamodb:UpdateItem"
              ],
              "Effect": "Allow",
              "Resource": [
                {
                  "Fn::GetAtt": [
                    "PostsTableC82B36F0",
                    "Arn"
                  ]
                },
                {
                  "Ref": "AWS::NoValue"
                }
              ]
            }
          ],
          "Version": "2012-10-17"
        },
        "PolicyName": "PostsFunctionServiceRoleDefaultPolicyACA3B729",
        "Roles": [
          {
            "Ref": "PostsFunctionServiceRoleF2DB8406"
          }
        ]
      },
      "Metadata": {
        "aws:cdk:path": "Project03CdkBasicStack/PostsFunction/ServiceRole/DefaultPolicy/Resource"
      }
    },
    "PostsFunction3DC4AEDB": {
      "Type": "AWS::Lambda::Function",
      "Properties": {
        "Code": {
          "S3Bucket": "cdk-lambda-deployment-bucket",
          "S3Key": "lambda.zip"
        },
        "Environment": {
          "Variables": {
            "TABLE_NAME": {
              "Ref": "PostsTableC82B36F0"
            }
          }
        },
        "Handler": "index.handler",
        "Role": {
          "Fn::GetAtt": [
            "PostsFunctionServiceRoleF2DB8406",
            "Arn"
          ]
        },
        "Runtime": "nodejs20.x"
      },
      "DependsOn": [
        "PostsFunctionServiceRoleDefaultPolicyACA3B729",
        "PostsFunctionServiceRoleF2DB8406"
      ],
      "Metadata": {
        "aws:cdk:path": "Project03CdkBasicStack/PostsFunction/Resource",
        "aws:asset:path": "asset.bde0c84c832acf14b6bc293a1e09327d0616dee901875f3157867c58a752324d",
        "aws:asset:is-bundled": false,
        "aws:asset:property": "Code"
      }
    },
    "PostsFunctionLogGroupC6FCA2A2": {
      "Type": "AWS::Logs::LogGroup",
      "Properties": {
        "LogGroupName": {
          "Fn::Join": [
            "",
            [
              "/aws/lambda/",
              {
                "Ref": "PostsFunction3DC4AEDB"
              }
            ]
          ]
        },
        "RetentionInDays": 731
      },
      "UpdateReplacePolicy": "Retain",
      "DeletionPolicy": "Retain",
      "Metadata": {
        "aws:cdk:path": "Project03CdkBasicStack/PostsFunction/LogGroup/Resource"
      }
    },
    "PostsApi3071F4B3": {
      "Type": "AWS::ApiGateway::RestApi",
      "Properties": {
        "Description": "API for managing posts",
        "Name": "Posts Service"
      },
      "Metadata": {
        "aws:cdk:path": "Project03CdkBasicStack/PostsApi/Resource"
      }
    },
    "PostsApiDeployment7D3D005De67a2f70b7e903e29d94fb529071a1e0": {
      "Type": "AWS::ApiGateway::Deployment",
      "Properties": {
        "Description": "API for managing posts",
        "RestApiId": {
          "Ref": "PostsApi3071F4B3"
        }
      },
      "DependsOn": [
        "PostsApiOPTIONSCE75E388",
        "PostsApipostsidDELETE16737D5E",
        "PostsApipostsidGET9B72BB71",
        "PostsApipostsidOPTIONSE6F9A6DF",
        "PostsApipostsidPUTB8247BF8",
        "PostsApipostsidBB97E669",
        "PostsApipostsGET34BA7DE4",
        "PostsApipostsOPTIONS2E79E562",
        "PostsApipostsPOSTD67FD8AE",
        "PostsApiposts2B6C6D66"
      ],
      "Metadata": {
        "aws:cdk:path": "Project03CdkBasicStack/PostsApi/Deployment/Resource",
        "aws:cdk:do-not-refactor": true
      }
    },
    "PostsApiDeploymentStageprod5F8E9068": {
      "Type": "AWS::ApiGateway::Stage",
      "Properties": {
        "DeploymentId": {
          "Ref": "PostsApiDeployment7D3D005De67a2f70b7e903e29d94fb529071a1e0"
        },
        "RestApiId": {
          "Ref": "PostsApi3071F4B3"
        },
        "StageName": "prod"
      },
      "Metadata": {
        "aws:cdk:path": "Project03CdkBasicStack/PostsApi/DeploymentStage.prod/Resource"
      }
    },
    "PostsApiOPTIONSCE75E388": {
      "Type": "AWS::ApiGateway::Method",
      "Properties": {
        "ApiKeyRequired": false,
        "AuthorizationType": "NONE",
        "HttpMethod": "OPTIONS",
        "Integration": {
          "IntegrationResponses": [
            {
              "ResponseParameters": {
                "method.response.header.Access-Control-Allow-Headers": "'Content-Type,X-Amz-Date,Authorization,X-Api-Key,X-Amz-Security-Token,X-Amz-User-Agent'",
                "method.response.header.Access-Control-Allow-Origin": "'*'",
                "method.response.header.Access-Control-Allow-Methods": "'OPTIONS,GET,PUT,POST,DELETE,PATCH,HEAD'"
              },
              "StatusCode": "204"
            }
          ],
          "RequestTemplates": {
            "application/json": "{ statusCode: 200 }"
          },
          "Type": "MOCK"
        },
        "MethodResponses": [
          {
            "ResponseParameters": {
              "method.response.header.Access-Control-Allow-Headers": true,
              "method.response.header.Access-Control-Allow-Origin": true,
              "method.response.header.Access-Control-Allow-Methods": true
            },
            "StatusCode": "204"
          }
        ],
        "ResourceId": {
          "Fn::GetAtt": [
            "PostsApi3071F4B3",
            "RootResourceId"
          ]
        },
        "RestApiId": {
          "Ref": "PostsApi3071F4B3"
        }
      },
      "Metadata": {
        "aws:cdk:path": "Project03CdkBasicStack/PostsApi/Default/OPTIONS/Resource"
      }
    },
    "PostsApiposts2B6C6D66": {
      "Type": "AWS::ApiGateway::Resource",
      "Properties": {
        "ParentId": {
          "Fn::GetAtt": [
            "PostsApi3071F4B3",
            "RootResourceId"
          ]
        },
        "PathPart": "posts",
        "RestApiId": {
          "Ref": "PostsApi3071F4B3"
        }
      },
      "Metadata": {
        "aws:cdk:path": "Project03CdkBasicStack/PostsApi/Default/posts/Resource"
      }
    },
    "PostsApipostsOPTIONS2E79E562": {
      "Type": "AWS::ApiGateway::Method",
      "Properties": {
        "ApiKeyRequired": false,
        "AuthorizationType": "NONE",
        "HttpMethod": "OPTIONS",
        "Integration": {
          "IntegrationResponses": [
            {
              "ResponseParameters": {
                "method.response.header.Access-Control-Allow-Headers": "'Content-Type,X-Amz-Date,Authorization,X-Api-Key,X-Amz-Security-Token,X-Amz-User-Agent'",
                "method.response.header.Access-Control-Allow-Origin": "'*'",
                "method.response.header.Access-Control-Allow-Methods": "'OPTIONS,GET,PUT,POST,DELETE,PATCH,HEAD'"
              },
              "StatusCode": "204"
            }
          ],
          "RequestTemplates": {
            "application/json": "{ statusCode: 200 }"
          },
          "Type": "MOCK"
        },
        "MethodResponses": [
          {
            "ResponseParameters": {
              "method.response.header.Access-Control-Allow-Headers": true,
              "method.response.header.Access-Control-Allow-Origin": true,
              "method.response.header.Access-Control-Allow-Methods": true
            },
            "StatusCode": "204"
          }
        ],
        "ResourceId": {
          "Ref": "PostsApiposts2B6C6D66"
        },
        "RestApiId": {
          "Ref": "PostsApi3071F4B3"
        }
      },
      "Metadata": {
        "aws:cdk:path": "Project03CdkBasicStack/PostsApi/Default/posts/OPTIONS/Resource"
      }
    },
    "PostsApipostsGETApiPermissionProject03CdkBasicStackPostsApiB04CEA04GETposts7AB057CE": {
      "Type": "AWS::Lambda::Permission",
      "Properties": {
        "Action": "lambda:InvokeFunction",
        "FunctionName": {
          "Fn::GetAtt": [
            "PostsFunction3DC4AEDB",
            "Arn"
          ]
        },
        "Principal": "apigateway.amazonaws.com",
        "SourceArn": {
          "Fn::Join": [
            "",
            [
              "arn:aws:execute-api:us-east-1:000000000000:",
              {
                "Ref": "PostsApi3071F4B3"
              },
              "/",
              {
                "Ref": "PostsApiDeploymentStageprod5F8E9068"
              },
              "/GET/posts"
            ]
          ]
        }
      },
      "Metadata": {
        "aws:cdk:path": "Project03CdkBasicStack/PostsApi/Default/posts/GET/ApiPermission.Project03CdkBasicStackPostsApiB04CEA04.GET..posts"
      }
    },
    "PostsApipostsGETApiPermissionTestProject03CdkBasicStackPostsApiB04CEA04GETposts3B70068C": {
      "Type": "AWS::Lambda::Permission",
      "Properties": {
        "Action": "lambda:InvokeFunction",
        "FunctionName": {
          "Fn::GetAtt": [
            "PostsFunction3DC4AEDB",
            "Arn"
          ]
        },
        "Principal": "apigateway.amazonaws.com",
        "SourceArn": {
          "Fn::Join": [
            "",
            [
              "arn:aws:execute-api:us-east-1:000000000000:",
              {
                "Ref": "PostsApi3071F4B3"
              },
              "/test-invoke-stage/GET/posts"
            ]
          ]
        }
      },
      "Metadata": {
        "aws:cdk:path": "Project03CdkBasicStack/PostsApi/Default/posts/GET/ApiPermission.Test.Project03CdkBasicStackPostsApiB04CEA04.GET..posts"
      }
    },
    "PostsApipostsGET34BA7DE4": {
      "Type": "AWS::ApiGateway::Method",
      "Properties": {
        "AuthorizationType": "NONE",
        "HttpMethod": "GET",
        "Integration": {
          "IntegrationHttpMethod": "POST",
          "Type": "AWS_PROXY",
          "Uri": {
            "Fn::Join": [
              "",
              [
                "arn:aws:apigateway:us-east-1:lambda:path/2015-03-31/functions/",
                {
                  "Fn::GetAtt": [
                    "PostsFunction3DC4AEDB",
                    "Arn"
                  ]
                },
                "/invocations"
              ]
            ]
          }
        },
        "ResourceId": {
          "Ref": "PostsApiposts2B6C6D66"
        },
        "RestApiId": {
          "Ref": "PostsApi3071F4B3"
        }
      },
      "Metadata": {
        "aws:cdk:path": "Project03CdkBasicStack/PostsApi/Default/posts/GET/Resource"
      }
    },
    "PostsApipostsPOSTApiPermissionProject03CdkBasicStackPostsApiB04CEA04POSTpostsDEE1B76E": {
      "Type": "AWS::Lambda::Permission",
      "Properties": {
        "Action": "lambda:InvokeFunction",
        "FunctionName": {
          "Fn::GetAtt": [
            "PostsFunction3DC4AEDB",
            "Arn"
          ]
        },
        "Principal": "apigateway.amazonaws.com",
        "SourceArn": {
          "Fn::Join": [
            "",
            [
              "arn:aws:execute-api:us-east-1:000000000000:",
              {
                "Ref": "PostsApi3071F4B3"
              },
              "/",
              {
                "Ref": "PostsApiDeploymentStageprod5F8E9068"
              },
              "/POST/posts"
            ]
          ]
        }
      },
      "Metadata": {
        "aws:cdk:path": "Project03CdkBasicStack/PostsApi/Default/posts/POST/ApiPermission.Project03CdkBasicStackPostsApiB04CEA04.POST..posts"
      }
    },
    "PostsApipostsPOSTApiPermissionTestProject03CdkBasicStackPostsApiB04CEA04POSTposts8547793F": {
      "Type": "AWS::Lambda::Permission",
      "Properties": {
        "Action": "lambda:InvokeFunction",
        "FunctionName": {
          "Fn::GetAtt": [
            "PostsFunction3DC4AEDB",
            "Arn"
          ]
        },
        "Principal": "apigateway.amazonaws.com",
        "SourceArn": {
          "Fn::Join": [
            "",
            [
              "arn:aws:execute-api:us-east-1:000000000000:",
              {
                "Ref": "PostsApi3071F4B3"
              },
              "/test-invoke-stage/POST/posts"
            ]
          ]
        }
      },
      "Metadata": {
        "aws:cdk:path": "Project03CdkBasicStack/PostsApi/Default/posts/POST/ApiPermission.Test.Project03CdkBasicStackPostsApiB04CEA04.POST..posts"
      }
    },
    "PostsApipostsPOSTD67FD8AE": {
      "Type": "AWS::ApiGateway::Method",
      "Properties": {
        "AuthorizationType": "NONE",
        "HttpMethod": "POST",
        "Integration": {
          "IntegrationHttpMethod": "POST",
          "Type": "AWS_PROXY",
          "Uri": {
            "Fn::Join": [
              "",
              [
                "arn:aws:apigateway:us-east-1:lambda:path/2015-03-31/functions/",
                {
                  "Fn::GetAtt": [
                    "PostsFunction3DC4AEDB",
                    "Arn"
                  ]
                },
                "/invocations"
              ]
            ]
          }
        },
        "ResourceId": {
          "Ref": "PostsApiposts2B6C6D66"
        },
        "RestApiId": {
          "Ref": "PostsApi3071F4B3"
        }
      },
      "Metadata": {
        "aws:cdk:path": "Project03CdkBasicStack/PostsApi/Default/posts/POST/Resource"
      }
    },
    "PostsApipostsidBB97E669": {
      "Type": "AWS::ApiGateway::Resource",
      "Properties": {
        "ParentId": {
          "Ref": "PostsApiposts2B6C6D66"
        },
        "PathPart": "{id}",
        "RestApiId": {
          "Ref": "PostsApi3071F4B3"
        }
      },
      "Metadata": {
        "aws:cdk:path": "Project03CdkBasicStack/PostsApi/Default/posts/{id}/Resource"
      }
    },
    "PostsApipostsidOPTIONSE6F9A6DF": {
      "Type": "AWS::ApiGateway::Method",
      "Properties": {
        "ApiKeyRequired": false,
        "AuthorizationType": "NONE",
        "HttpMethod": "OPTIONS",
        "Integration": {
          "IntegrationResponses": [
            {
              "ResponseParameters": {
                "method.response.header.Access-Control-Allow-Headers": "'Content-Type,X-Amz-Date,Authorization,X-Api-Key,X-Amz-Security-Token,X-Amz-User-Agent'",
                "method.response.header.Access-Control-Allow-Origin": "'*'",
                "method.response.header.Access-Control-Allow-Methods": "'OPTIONS,GET,PUT,POST,DELETE,PATCH,HEAD'"
              },
              "StatusCode": "204"
            }
          ],
          "RequestTemplates": {
            "application/json": "{ statusCode: 200 }"
          },
          "Type": "MOCK"
        },
        "MethodResponses": [
          {
            "ResponseParameters": {
              "method.response.header.Access-Control-Allow-Headers": true,
              "method.response.header.Access-Control-Allow-Origin": true,
              "method.response.header.Access-Control-Allow-Methods": true
            },
            "StatusCode": "204"
          }
        ],
        "ResourceId": {
          "Ref": "PostsApipostsidBB97E669"
        },
        "RestApiId": {
          "Ref": "PostsApi3071F4B3"
        }
      },
      "Metadata": {
        "aws:cdk:path": "Project03CdkBasicStack/PostsApi/Default/posts/{id}/OPTIONS/Resource"
      }
    },
    "PostsApipostsidGETApiPermissionProject03CdkBasicStackPostsApiB04CEA04GETpostsid2CE8E6B8": {
      "Type": "AWS::Lambda::Permission",
      "Properties": {
        "Action": "lambda:InvokeFunction",
        "FunctionName": {
          "Fn::GetAtt": [
            "PostsFunction3DC4AEDB",
            "Arn"
          ]
        },
        "Principal": "apigateway.amazonaws.com",
        "SourceArn": {
          "Fn::Join": [
            "",
            [
              "arn:aws:execute-api:us-east-1:000000000000:",
              {
                "Ref": "PostsApi3071F4B3"
              },
              "/",
              {
                "Ref": "PostsApiDeploymentStageprod5F8E9068"
              },
              "/GET/posts/*"
            ]
          ]
        }
      },
      "Metadata": {
        "aws:cdk:path": "Project03CdkBasicStack/PostsApi/Default/posts/{id}/GET/ApiPermission.Project03CdkBasicStackPostsApiB04CEA04.GET..posts.{id}"
      }
    },
    "PostsApipostsidGETApiPermissionTestProject03CdkBasicStackPostsApiB04CEA04GETpostsid678299AA": {
      "Type": "AWS::Lambda::Permission",
      "Properties": {
        "Action": "lambda:InvokeFunction",
        "FunctionName": {
          "Fn::GetAtt": [
            "PostsFunction3DC4AEDB",
            "Arn"
          ]
        },
        "Principal": "apigateway.amazonaws.com",
        "SourceArn": {
          "Fn::Join": [
            "",
            [
              "arn:aws:execute-api:us-east-1:000000000000:",
              {
                "Ref": "PostsApi3071F4B3"
              },
              "/test-invoke-stage/GET/posts/*"
            ]
          ]
        }
      },
      "Metadata": {
        "aws:cdk:path": "Project03CdkBasicStack/PostsApi/Default/posts/{id}/GET/ApiPermission.Test.Project03CdkBasicStackPostsApiB04CEA04.GET..posts.{id}"
      }
    },
    "PostsApipostsidGET9B72BB71": {
      "Type": "AWS::ApiGateway::Method",
      "Properties": {
        "AuthorizationType": "NONE",
        "HttpMethod": "GET",
        "Integration": {
          "IntegrationHttpMethod": "POST",
          "Type": "AWS_PROXY",
          "Uri": {
            "Fn::Join": [
              "",
              [
                "arn:aws:apigateway:us-east-1:lambda:path/2015-03-31/functions/",
                {
                  "Fn::GetAtt": [
                    "PostsFunction3DC4AEDB",
                    "Arn"
                  ]
                },
                "/invocations"
              ]
            ]
          }
        },
        "ResourceId": {
          "Ref": "PostsApipostsidBB97E669"
        },
        "RestApiId": {
          "Ref": "PostsApi3071F4B3"
        }
      },
      "Metadata": {
        "aws:cdk:path": "Project03CdkBasicStack/PostsApi/Default/posts/{id}/GET/Resource"
      }
    },
    "PostsApipostsidPUTApiPermissionProject03CdkBasicStackPostsApiB04CEA04PUTpostsidC721CF73": {
      "Type": "AWS::Lambda::Permission",
      "Properties": {
        "Action": "lambda:InvokeFunction",
        "FunctionName": {
          "Fn::GetAtt": [
            "PostsFunction3DC4AEDB",
            "Arn"
          ]
        },
        "Principal": "apigateway.amazonaws.com",
        "SourceArn": {
          "Fn::Join": [
            "",
            [
              "arn:aws:execute-api:us-east-1:000000000000:",
              {
                "Ref": "PostsApi3071F4B3"
              },
              "/",
              {
                "Ref": "PostsApiDeploymentStageprod5F8E9068"
              },
              "/PUT/posts/*"
            ]
          ]
        }
      },
      "Metadata": {
        "aws:cdk:path": "Project03CdkBasicStack/PostsApi/Default/posts/{id}/PUT/ApiPermission.Project03CdkBasicStackPostsApiB04CEA04.PUT..posts.{id}"
      }
    },
    "PostsApipostsidPUTApiPermissionTestProject03CdkBasicStackPostsApiB04CEA04PUTpostsidBB628E7B": {
      "Type": "AWS::Lambda::Permission",
      "Properties": {
        "Action": "lambda:InvokeFunction",
        "FunctionName": {
          "Fn::GetAtt": [
            "PostsFunction3DC4AEDB",
            "Arn"
          ]
        },
        "Principal": "apigateway.amazonaws.com",
        "SourceArn": {
          "Fn::Join": [
            "",
            [
              "arn:aws:execute-api:us-east-1:000000000000:",
              {
                "Ref": "PostsApi3071F4B3"
              },
              "/test-invoke-stage/PUT/posts/*"
            ]
          ]
        }
      },
      "Metadata": {
        "aws:cdk:path": "Project03CdkBasicStack/PostsApi/Default/posts/{id}/PUT/ApiPermission.Test.Project03CdkBasicStackPostsApiB04CEA04.PUT..posts.{id}"
      }
    },
    "PostsApipostsidPUTB8247BF8": {
      "Type": "AWS::ApiGateway::Method",
      "Properties": {
        "AuthorizationType": "NONE",
        "HttpMethod": "PUT",
        "Integration": {
          "IntegrationHttpMethod": "POST",
          "Type": "AWS_PROXY",
          "Uri": {
            "Fn::Join": [
              "",
              [
                "arn:aws:apigateway:us-east-1:lambda:path/2015-03-31/functions/",
                {
                  "Fn::GetAtt": [
                    "PostsFunction3DC4AEDB",
                    "Arn"
                  ]
                },
                "/invocations"
              ]
            ]
          }
        },
        "ResourceId": {
          "Ref": "PostsApipostsidBB97E669"
        },
        "RestApiId": {
          "Ref": "PostsApi3071F4B3"
        }
      },
      "Metadata": {
        "aws:cdk:path": "Project03CdkBasicStack/PostsApi/Default/posts/{id}/PUT/Resource"
      }
    },
    "PostsApipostsidDELETEApiPermissionProject03CdkBasicStackPostsApiB04CEA04DELETEpostsid1EB54CEC": {
      "Type": "AWS::Lambda::Permission",
      "Properties": {
        "Action": "lambda:InvokeFunction",
        "FunctionName": {
          "Fn::GetAtt": [
            "PostsFunction3DC4AEDB",
            "Arn"
          ]
        },
        "Principal": "apigateway.amazonaws.com",
        "SourceArn": {
          "Fn::Join": [
            "",
            [
              "arn:aws:execute-api:us-east-1:000000000000:",
              {
                "Ref": "PostsApi3071F4B3"
              },
              "/",
              {
                "Ref": "PostsApiDeploymentStageprod5F8E9068"
              },
              "/DELETE/posts/*"
            ]
          ]
        }
      },
      "Metadata": {
        "aws:cdk:path": "Project03CdkBasicStack/PostsApi/Default/posts/{id}/DELETE/ApiPermission.Project03CdkBasicStackPostsApiB04CEA04.DELETE..posts.{id}"
      }
    },
    "PostsApipostsidDELETEApiPermissionTestProject03CdkBasicStackPostsApiB04CEA04DELETEpostsid9B7E1E46": {
      "Type": "AWS::Lambda::Permission",
      "Properties": {
        "Action": "lambda:InvokeFunction",
        "FunctionName": {
          "Fn::GetAtt": [
            "PostsFunction3DC4AEDB",
            "Arn"
          ]
        },
        "Principal": "apigateway.amazonaws.com",
        "SourceArn": {
          "Fn::Join": [
            "",
            [
              "arn:aws:execute-api:us-east-1:000000000000:",
              {
                "Ref": "PostsApi3071F4B3"
              },
              "/test-invoke-stage/DELETE/posts/*"
            ]
          ]
        }
      },
      "Metadata": {
        "aws:cdk:path": "Project03CdkBasicStack/PostsApi/Default/posts/{id}/DELETE/ApiPermission.Test.Project03CdkBasicStackPostsApiB04CEA04.DELETE..posts.{id}"
      }
    },
    "PostsApipostsidDELETE16737D5E": {
      "Type": "AWS::ApiGateway::Method",
      "Properties": {
        "AuthorizationType": "NONE",
        "HttpMethod": "DELETE",
        "Integration": {
          "IntegrationHttpMethod": "POST",
          "Type": "AWS_PROXY",
          "Uri": {
            "Fn::Join": [
              "",
              [
                "arn:aws:apigateway:us-east-1:lambda:path/2015-03-31/functions/",
                {
                  "Fn::GetAtt": [
                    "PostsFunction3DC4AEDB",
                    "Arn"
                  ]
                },
                "/invocations"
              ]
            ]
          }
        },
        "ResourceId": {
          "Ref": "PostsApipostsidBB97E669"
        },
        "RestApiId": {
          "Ref": "PostsApi3071F4B3"
        }
      },
      "Metadata": {
        "aws:cdk:path": "Project03CdkBasicStack/PostsApi/Default/posts/{id}/DELETE/Resource"
      }
    },
    "CDKMetadata": {
      "Type": "AWS::CDK::Metadata",
      "Properties": {
        "Analytics": "v2:deflate64:H4sIAAAAAAAA/+1WS2/bMAz+LdWxUL2l3S65pV02FH15TnYYjCBgLMZRK0ueJDfwDP/3QQ8nKboV2GXDhp5MfaQ+ig/ROk1OR++Tt0ewNScFezgRfJV0MwvFA4WtWXaslVAptkq6OawE5h2pQVtuuZJX2JJxRyRUSMbkmFBi29qJM9JTsuJCcFneKOagdPJ1mU6zZTb9/GU6mxNKNFbqEUSqBC9aMiYMjdWqJf2CXqyld9ZTAdWKQdJ9bGThXOYd0Y20fOexCPRO3IBkAnVcoXzkWskKpfVITzsCjE0P4dxbHpNF8Dk4cXKKuuLGcCV7yqFKukz54MGYpkJ27iOvNZcFr0FMikI10RGNNm7DxPNF/6QCCSUyHzFHQ8Z59wRrJzraLuJp5yodXAx5yruotRaKzaUUXOJO52N5UekDdUejAfcpGDbMldM843kOMzazYNFl0cQjeeLA2VNztgRj0Jpk4j7UnCXnTfGA9hwM5gsqVGmS7lqVn7Rq6rwjIoq3Qy8FvsGip1DzEixuoU26DI2d1Nz1QpBu9x3I0BSa17u0O2QNjbAXSptU41rwcmPvvIFxNQQh1PZO85K7daifg27QbhQLUB/TFrzRD1gL1brg8+4nDqHmUdJogcu9uTnsxLm6ViUvQFyyg6r+j7hP3j4LdGahRJ+6AToouVfSDI1qdIG+X1zb0VCPUHOvGm69tXXQRYBLi6WGg4Kog2o3dqM0/+7GxOHqctg9QH7/PIwzf3mh5lfYZvit4RoZGa9BGPyVPSWVP1KGplbSxLtuLNjGXOwnlo7qFDRUaFGb4frHXN48YfldEvqarD+VrHit/yrDa8H+sYLtZl7YsBt64Y2Fu/dEDXaTgt6/Y17QDj8qT9T3e87hqUP9H9lNWS5LZ3zX2LqxPZWKYXJv3jyevktGo2R0dG84P4mvrSQL3x/HH4E1LgoAAA=="
      },
      "Metadata": {
        "aws:cdk:path": "Project03CdkBasicStack/CDKMetadata/Default"
      }
    }
  },
  "Outputs": {
    "PostsApiEndpoint56996E10": {
      "Value": {
        "Fn::Join": [
          "",
          [
            "https://",
            {
              "Ref": "PostsApi3071F4B3"
            },
            ".execute-api.us-east-1.",
            {
              "Ref": "AWS::URLSuffix"
            },
            "/",
            {
              "Ref": "PostsApiDeploymentStageprod5F8E9068"
            },
            "/"
          ]
        ]
      }
    },
    "ApiUrl": {
      "Description": "API Gateway URL",
      "Value": {
        "Fn::Join": [
          "",
          [
            "https://",
            {
              "Ref": "PostsApi3071F4B3"
            },
            ".execute-api.us-east-1.",
            {
              "Ref": "AWS::URLSuffix"
            },
            "/",
            {
              "Ref": "PostsApiDeploymentStageprod5F8E9068"
            },
            "/"
          ]
        ]
      }
    },
    "TableName": {
      "Description": "DynamoDB Table Name",
      "Value": {
        "Ref": "PostsTableC82B36F0"
      }
    }
  },
  "Parameters": {}
}
